cukcuk/__init__.py
cukcuk/async_login_session.py
cukcuk/branch.py
cukcuk/common.py
cukcuk/invoice.py
cukcuk/login_session.py
cukcuk/storage.py
cukcuk-0.5.3.dist-info/METADATA
cukcuk-0.5.3.dist-info/WHEEL
cukcuk-0.5.3.dist-info/top_level.txt
cukcuk-0.5.3.dist-info/RECORD
