Metadata-Version: 2.1
Name: cukcuk
Version: 0.5.3
Summary: Connect to Cukcuk Shop API
Author-email: Minh Bui <buiducminh287@gmail.com>
Requires-Python: >=3.8
Requires-Dist: aiohttp (>=3.8)
Requires-Dist: requests (>=2)
Requires-Dist: sqlalchemy (>=2)
Requires-Dist: pytz
Requires-Dist: pandas (>=2.0)
